{
  "relationships_followers": [
    {
      "title": "",
      "media_list_data": [
        
      ],
      "string_list_data": [
        {
          "href": "https://www.instagram.com/shawn.teh",
          "value": "shawn.teh",
          "timestamp": 1646455222
        }
      ]
    },
    {
      "title": "",
      "media_list_data": [
        
      ],
      "string_list_data": [
        {
          "href": "https://www.instagram.com/potota_luo",
          "value": "potota_luo",
          "timestamp": 1646106623
        }
      ]
    },
    {
      "title": "",
      "media_list_data": [
        
      ],
      "string_list_data": [
        {
          "href": "https://www.instagram.com/stephaniesalewski",
          "value": "stephaniesalewski",
          "timestamp": 1646095730
        }
      ]
    },
    {
      "title": "",
      "media_list_data": [
        
      ],
      "string_list_data": [
        {
          "href": "https://www.instagram.com/eisha.hermo",
          "value": "eisha.hermo",
          "timestamp": 1646083018
        }
      ]
    },
    {
      "title": "",
      "media_list_data": [
        
      ],
      "string_list_data": [
        {
          "href": "https://www.instagram.com/h_anna.jung",
          "value": "h_anna.jung",
          "timestamp": 1646016047
        }
      ]
    },
    {
      "title": "",
      "media_list_data": [
        
      ],
      "string_list_data": [
        {
          "href": "https://www.instagram.com/uoftfreelancers",
          "value": "uoftfreelancers",
          "timestamp": 1645768866
        }
      ]
    },
    {
      "title": "",
      "media_list_data": [
        
      ],
      "string_list_data": [
        {
          "href": "https://www.instagram.com/tyler.jon.wong",
          "value": "tyler.jon.wong",
          "timestamp": 1645768865
        }
      ]
    },
    {
      "title": "",
      "media_list_data": [
        
      ],
      "string_list_data": [
        {
          "href": "https://www.instagram.com/jin_bbang319",
          "value": "jin_bbang319",
          "timestamp": 1645030452
        }
      ]
    },
    {
      "title": "",
      "media_list_data": [
        
      ],
      "string_list_data": [
        {
          "href": "https://www.instagram.com/toniedun1",
          "value": "toniedun1",
          "timestamp": 1644735822
        }
      ]
    },
    {
      "title": "",
      "media_list_data": [
        
      ],
      "string_list_data": [
        {
          "href": "https://www.instagram.com/helenlliu",
          "value": "helenlliu",
          "timestamp": 1644735816
        }
      ]
    },
    {
      "title": "",
      "media_list_data": [
        
      ],
      "string_list_data": [
        {
          "href": "https://www.instagram.com/canaliphil",
          "value": "canaliphil",
          "timestamp": 1643435137
        }
      ]
    },
    {
      "title": "",
      "media_list_data": [
        
      ],
      "string_list_data": [
        {
          "href": "https://www.instagram.com/h_amza.m",
          "value": "h_amza.m",
          "timestamp": 1643168574
        }
      ]
    },
    {
      "title": "",
      "media_list_data": [
        
      ],
      "string_list_data": [
        {
          "href": "https://www.instagram.com/tran5863",
          "value": "tran5863",
          "timestamp": 1643168569
        }
      ]
    },
    {
      "title": "",
      "media_list_data": [
        
      ],
      "string_list_data": [
        {
          "href": "https://www.instagram.com/kanchayayaya",
          "value": "kanchayayaya",
          "timestamp": 1643168562
        }
      ]
    },
    {
      "title": "",
      "media_list_data": [
        
      ],
      "string_list_data": [
        {
          "href": "https://www.instagram.com/lisa.mtui",
          "value": "lisa.mtui",
          "timestamp": 1643168553
        }
      ]
    },
    {
      "title": "",
      "media_list_data": [
        
      ],
      "string_list_data": [
        {
          "href": "https://www.instagram.com/tahseengpavel24",
          "value": "tahseengpavel24",
          "timestamp": 1642640405
        }
      ]
    },
    {
      "title": "",
      "media_list_data": [
        
      ],
      "string_list_data": [
        {
          "href": "https://www.instagram.com/skylarkning",
          "value": "skylarkning",
          "timestamp": 1642375488
        }
      ]
    },
    {
      "title": "",
      "media_list_data": [
        
      ],
      "string_list_data": [
        {
          "href": "https://www.instagram.com/ryojohanf",
          "value": "ryojohanf",
          "timestamp": 1642296899
        }
      ]
    },
    {
      "title": "",
      "media_list_data": [
        
      ],
      "string_list_data": [
        {
          "href": "https://www.instagram.com/em_a.a.n",
          "value": "em_a.a.n",
          "timestamp": 1642252347
        }
      ]
    },
    {
      "title": "",
      "media_list_data": [
        
      ],
      "string_list_data": [
        {
          "href": "https://www.instagram.com/mchllesun",
          "value": "mchllesun",
          "timestamp": 1642252346
        }
      ]
    },
    {
      "title": "",
      "media_list_data": [
        
      ],
      "string_list_data": [
        {
          "href": "https://www.instagram.com/vincentgu88",
          "value": "vincentgu88",
          "timestamp": 1642252345
        }
      ]
    },
    {
      "title": "",
      "media_list_data": [
        
      ],
      "string_list_data": [
        {
          "href": "https://www.instagram.com/vanness.yxxg",
          "value": "vanness.yxxg",
          "timestamp": 1642139518
        }
      ]
    },
    {
      "title": "",
      "media_list_data": [
        
      ],
      "string_list_data": [
        {
          "href": "https://www.instagram.com/edlynliii",
          "value": "edlynliii",
          "timestamp": 1642109341
        }
      ]
    },
    {
      "title": "",
      "media_list_data": [
        
      ],
      "string_list_data": [
        {
          "href": "https://www.instagram.com/jeremymutd",
          "value": "jeremymutd",
          "timestamp": 1642054054
        }
      ]
    },
    {
      "title": "",
      "media_list_data": [
        
      ],
      "string_list_data": [
        {
          "href": "https://www.instagram.com/_jackyliao_",
          "value": "_jackyliao_",
          "timestamp": 1642054019
        }
      ]
    },
    {
      "title": "",
      "media_list_data": [
        
      ],
      "string_list_data": [
        {
          "href": "https://www.instagram.com/khushi.niranjan",
          "value": "khushi.niranjan",
          "timestamp": 1642054012
        }
      ]
    },
    {
      "title": "",
      "media_list_data": [
        
      ],
      "string_list_data": [
        {
          "href": "https://www.instagram.com/quinn_lwk",
          "value": "quinn_lwk",
          "timestamp": 1641538552
        }
      ]
    },
    {
      "title": "",
      "media_list_data": [
        
      ],
      "string_list_data": [
        {
          "href": "https://www.instagram.com/ayy.jude",
          "value": "ayy.jude",
          "timestamp": 1641321615
        }
      ]
    },
    {
      "title": "",
      "media_list_data": [
        
      ],
      "string_list_data": [
        {
          "href": "https://www.instagram.com/2t5froshprank",
          "value": "2t5froshprank",
          "timestamp": 1640854669
        }
      ]
    },
    {
      "title": "",
      "media_list_data": [
        
      ],
      "string_list_data": [
        {
          "href": "https://www.instagram.com/ashlxyzz",
          "value": "ashlxyzz",
          "timestamp": 1639596030
        }
      ]
    },
    {
      "title": "",
      "media_list_data": [
        
      ],
      "string_list_data": [
        {
          "href": "https://www.instagram.com/michael.jpn",
          "value": "michael.jpn",
          "timestamp": 1639596022
        }
      ]
    },
    {
      "title": "",
      "media_list_data": [
        
      ],
      "string_list_data": [
        {
          "href": "https://www.instagram.com/goodkingcole",
          "value": "goodkingcole",
          "timestamp": 1637970787
        }
      ]
    },
    {
      "title": "",
      "media_list_data": [
        
      ],
      "string_list_data": [
        {
          "href": "https://www.instagram.com/liam.krestow",
          "value": "liam.krestow",
          "timestamp": 1637628203
        }
      ]
    },
    {
      "title": "",
      "media_list_data": [
        
      ],
      "string_list_data": [
        {
          "href": "https://www.instagram.com/sunkk2442",
          "value": "sunkk2442",
          "timestamp": 1637628202
        }
      ]
    },
    {
      "title": "",
      "media_list_data": [
        
      ],
      "string_list_data": [
        {
          "href": "https://www.instagram.com/baaasellll",
          "value": "baaasellll",
          "timestamp": 1637593083
        }
      ]
    },
    {
      "title": "",
      "media_list_data": [
        
      ],
      "string_list_data": [
        {
          "href": "https://www.instagram.com/noratawfiq",
          "value": "noratawfiq",
          "timestamp": 1637593076
        }
      ]
    },
    {
      "title": "",
      "media_list_data": [
        
      ],
      "string_list_data": [
        {
          "href": "https://www.instagram.com/kate.y_star",
          "value": "kate.y_star",
          "timestamp": 1637453891
        }
      ]
    },
    {
      "title": "",
      "media_list_data": [
        
      ],
      "string_list_data": [
        {
          "href": "https://www.instagram.com/sydney.quach",
          "value": "sydney.quach",
          "timestamp": 1637453890
        }
      ]
    },
    {
      "title": "",
      "media_list_data": [
        
      ],
      "string_list_data": [
        {
          "href": "https://www.instagram.com/sritejas.murugan",
          "value": "sritejas.murugan",
          "timestamp": 1637072427
        }
      ]
    },
    {
      "title": "",
      "media_list_data": [
        
      ],
      "string_list_data": [
        {
          "href": "https://www.instagram.com/francesco.culmone",
          "value": "francesco.culmone",
          "timestamp": 1636254461
        }
      ]
    },
    {
      "title": "",
      "media_list_data": [
        
      ],
      "string_list_data": [
        {
          "href": "https://www.instagram.com/weeaboo_kiddo",
          "value": "weeaboo_kiddo",
          "timestamp": 1635620074
        }
      ]
    },
    {
      "title": "",
      "media_list_data": [
        
      ],
      "string_list_data": [
        {
          "href": "https://www.instagram.com/vgnzlo",
          "value": "vgnzlo",
          "timestamp": 1635538896
        }
      ]
    },
    {
      "title": "",
      "media_list_data": [
        
      ],
      "string_list_data": [
        {
          "href": "https://www.instagram.com/emilyvituong",
          "value": "emilyvituong",
          "timestamp": 1635209782
        }
      ]
    },
    {
      "title": "",
      "media_list_data": [
        
      ],
      "string_list_data": [
        {
          "href": "https://www.instagram.com/policy.advocacy.ewb",
          "value": "policy.advocacy.ewb",
          "timestamp": 1634394277
        }
      ]
    },
    {
      "title": "",
      "media_list_data": [
        
      ],
      "string_list_data": [
        {
          "href": "https://www.instagram.com/joshua._.li",
          "value": "joshua._.li",
          "timestamp": 1634355076
        }
      ]
    },
    {
      "title": "",
      "media_list_data": [
        
      ],
      "string_list_data": [
        {
          "href": "https://www.instagram.com/c.eciliatan",
          "value": "c.eciliatan",
          "timestamp": 1633730616
        }
      ]
    },
    {
      "title": "",
      "media_list_data": [
        
      ],
      "string_list_data": [
        {
          "href": "https://www.instagram.com/sbj_12321",
          "value": "sbj_12321",
          "timestamp": 1633730615
        }
      ]
    },
    {
      "title": "",
      "media_list_data": [
        
      ],
      "string_list_data": [
        {
          "href": "https://www.instagram.com/namiel1129",
          "value": "namiel1129",
          "timestamp": 1633666425
        }
      ]
    },
    {
      "title": "",
      "media_list_data": [
        
      ],
      "string_list_data": [
        {
          "href": "https://www.instagram.com/nguy.rn_",
          "value": "nguy.rn_",
          "timestamp": 1633666421
        }
      ]
    },
    {
      "title": "",
      "media_list_data": [
        
      ],
      "string_list_data": [
        {
          "href": "https://www.instagram.com/antoniotripodii",
          "value": "antoniotripodii",
          "timestamp": 1633577349
        }
      ]
    },
    {
      "title": "",
      "media_list_data": [
        
      ],
      "string_list_data": [
        {
          "href": "https://www.instagram.com/natalie_wns",
          "value": "natalie_wns",
          "timestamp": 1633535617
        }
      ]
    },
    {
      "title": "",
      "media_list_data": [
        
      ],
      "string_list_data": [
        {
          "href": "https://www.instagram.com/jphongngo",
          "value": "jphongngo",
          "timestamp": 1633318312
        }
      ]
    },
    {
      "title": "",
      "media_list_data": [
        
      ],
      "string_list_data": [
        {
          "href": "https://www.instagram.com/brianli.17",
          "value": "brianli.17",
          "timestamp": 1633151599
        }
      ]
    },
    {
      "title": "",
      "media_list_data": [
        
      ],
      "string_list_data": [
        {
          "href": "https://www.instagram.com/ayleenf_",
          "value": "ayleenf_",
          "timestamp": 1633144889
        }
      ]
    },
    {
      "title": "",
      "media_list_data": [
        
      ],
      "string_list_data": [
        {
          "href": "https://www.instagram.com/_arthea",
          "value": "_arthea",
          "timestamp": 1632970996
        }
      ]
    },
    {
      "title": "",
      "media_list_data": [
        
      ],
      "string_list_data": [
        {
          "href": "https://www.instagram.com/edmondlams",
          "value": "edmondlams",
          "timestamp": 1632778203
        }
      ]
    },
    {
      "title": "",
      "media_list_data": [
        
      ],
      "string_list_data": [
        {
          "href": "https://www.instagram.com/mahnemm",
          "value": "mahnemm",
          "timestamp": 1632778202
        }
      ]
    },
    {
      "title": "",
      "media_list_data": [
        
      ],
      "string_list_data": [
        {
          "href": "https://www.instagram.com/tarandeep_l",
          "value": "tarandeep_l",
          "timestamp": 1632775435
        }
      ]
    },
    {
      "title": "",
      "media_list_data": [
        
      ],
      "string_list_data": [
        {
          "href": "https://www.instagram.com/novera.engsci.rep",
          "value": "novera.engsci.rep",
          "timestamp": 1632717849
        }
      ]
    },
    {
      "title": "",
      "media_list_data": [
        
      ],
      "string_list_data": [
        {
          "href": "https://www.instagram.com/alekseygoro",
          "value": "alekseygoro",
          "timestamp": 1632717834
        }
      ]
    },
    {
      "title": "",
      "media_list_data": [
        
      ],
      "string_list_data": [
        {
          "href": "https://www.instagram.com/ayleenclassrep",
          "value": "ayleenclassrep",
          "timestamp": 1632692873
        }
      ]
    },
    {
      "title": "",
      "media_list_data": [
        
      ],
      "string_list_data": [
        {
          "href": "https://www.instagram.com/jenna.slater03",
          "value": "jenna.slater03",
          "timestamp": 1632443877
        }
      ]
    },
    {
      "title": "",
      "media_list_data": [
        
      ],
      "string_list_data": [
        {
          "href": "https://www.instagram.com/bddhjdjsjsjsjsjs",
          "value": "bddhjdjsjsjsjsjs",
          "timestamp": 1632432448
        }
      ]
    },
    {
      "title": "",
      "media_list_data": [
        
      ],
      "string_list_data": [
        {
          "href": "https://www.instagram.com/chewychuchuchew",
          "value": "chewychuchuchew",
          "timestamp": 1632432446
        }
      ]
    },
    {
      "title": "",
      "media_list_data": [
        
      ],
      "string_list_data": [
        {
          "href": "https://www.instagram.com/britney_trinh",
          "value": "britney_trinh",
          "timestamp": 1631839464
        }
      ]
    },
    {
      "title": "",
      "media_list_data": [
        
      ],
      "string_list_data": [
        {
          "href": "https://www.instagram.com/zhanger23",
          "value": "zhanger23",
          "timestamp": 1631839463
        }
      ]
    },
    {
      "title": "",
      "media_list_data": [
        
      ],
      "string_list_data": [
        {
          "href": "https://www.instagram.com/theakristiana",
          "value": "theakristiana",
          "timestamp": 1631720621
        }
      ]
    },
    {
      "title": "",
      "media_list_data": [
        
      ],
      "string_list_data": [
        {
          "href": "https://www.instagram.com/_toobaelahi",
          "value": "_toobaelahi",
          "timestamp": 1631651597
        }
      ]
    },
    {
      "title": "",
      "media_list_data": [
        
      ],
      "string_list_data": [
        {
          "href": "https://www.instagram.com/_aravindsubramanian",
          "value": "_aravindsubramanian",
          "timestamp": 1631651595
        }
      ]
    },
    {
      "title": "",
      "media_list_data": [
        
      ],
      "string_list_data": [
        {
          "href": "https://www.instagram.com/step_hen_l",
          "value": "step_hen_l",
          "timestamp": 1631548895
        }
      ]
    },
    {
      "title": "",
      "media_list_data": [
        
      ],
      "string_list_data": [
        {
          "href": "https://www.instagram.com/imperviouschao",
          "value": "imperviouschao",
          "timestamp": 1631548892
        }
      ]
    },
    {
      "title": "",
      "media_list_data": [
        
      ],
      "string_list_data": [
        {
          "href": "https://www.instagram.com/skim1601",
          "value": "skim1601",
          "timestamp": 1631548890
        }
      ]
    },
    {
      "title": "",
      "media_list_data": [
        
      ],
      "string_list_data": [
        {
          "href": "https://www.instagram.com/s.skarn",
          "value": "s.skarn",
          "timestamp": 1631548889
        }
      ]
    },
    {
      "title": "",
      "media_list_data": [
        
      ],
      "string_list_data": [
        {
          "href": "https://www.instagram.com/chris.canelea",
          "value": "chris.canelea",
          "timestamp": 1631540808
        }
      ]
    },
    {
      "title": "",
      "media_list_data": [
        
      ],
      "string_list_data": [
        {
          "href": "https://www.instagram.com/yncnuoft",
          "value": "yncnuoft",
          "timestamp": 1631304142
        }
      ]
    },
    {
      "title": "",
      "media_list_data": [
        
      ],
      "string_list_data": [
        {
          "href": "https://www.instagram.com/sa.fc",
          "value": "sa.fc",
          "timestamp": 1631212334
        }
      ]
    },
    {
      "title": "",
      "media_list_data": [
        
      ],
      "string_list_data": [
        {
          "href": "https://www.instagram.com/_.anna_mxria",
          "value": "_.anna_mxria",
          "timestamp": 1631159297
        }
      ]
    },
    {
      "title": "",
      "media_list_data": [
        
      ],
      "string_list_data": [
        {
          "href": "https://www.instagram.com/z.mark11",
          "value": "z.mark11",
          "timestamp": 1631159294
        }
      ]
    },
    {
      "title": "",
      "media_list_data": [
        
      ],
      "string_list_data": [
        {
          "href": "https://www.instagram.com/vicladash",
          "value": "vicladash",
          "timestamp": 1631072331
        }
      ]
    },
    {
      "title": "",
      "media_list_data": [
        
      ],
      "string_list_data": [
        {
          "href": "https://www.instagram.com/duzunn",
          "value": "duzunn",
          "timestamp": 1631072328
        }
      ]
    },
    {
      "title": "",
      "media_list_data": [
        
      ],
      "string_list_data": [
        {
          "href": "https://www.instagram.com/0okram",
          "value": "0okram",
          "timestamp": 1631072314
        }
      ]
    },
    {
      "title": "",
      "media_list_data": [
        
      ],
      "string_list_data": [
        {
          "href": "https://www.instagram.com/stephxnielu",
          "value": "stephxnielu",
          "timestamp": 1631072309
        }
      ]
    },
    {
      "title": "",
      "media_list_data": [
        
      ],
      "string_list_data": [
        {
          "href": "https://www.instagram.com/maurodeliberato",
          "value": "maurodeliberato",
          "timestamp": 1631048522
        }
      ]
    },
    {
      "title": "",
      "media_list_data": [
        
      ],
      "string_list_data": [
        {
          "href": "https://www.instagram.com/hazelfricska",
          "value": "hazelfricska",
          "timestamp": 1631048444
        }
      ]
    },
    {
      "title": "",
      "media_list_data": [
        
      ],
      "string_list_data": [
        {
          "href": "https://www.instagram.com/morelliamanda_",
          "value": "morelliamanda_",
          "timestamp": 1631048435
        }
      ]
    },
    {
      "title": "",
      "media_list_data": [
        
      ],
      "string_list_data": [
        {
          "href": "https://www.instagram.com/lucas.sait0",
          "value": "lucas.sait0",
          "timestamp": 1630985969
        }
      ]
    },
    {
      "title": "",
      "media_list_data": [
        
      ],
      "string_list_data": [
        {
          "href": "https://www.instagram.com/meet_patel2580",
          "value": "meet_patel2580",
          "timestamp": 1630950127
        }
      ]
    },
    {
      "title": "",
      "media_list_data": [
        
      ],
      "string_list_data": [
        {
          "href": "https://www.instagram.com/tsigmund66",
          "value": "tsigmund66",
          "timestamp": 1630807539
        }
      ]
    },
    {
      "title": "",
      "media_list_data": [
        
      ],
      "string_list_data": [
        {
          "href": "https://www.instagram.com/haydeng30",
          "value": "haydeng30",
          "timestamp": 1630303132
        }
      ]
    },
    {
      "title": "",
      "media_list_data": [
        
      ],
      "string_list_data": [
        {
          "href": "https://www.instagram.com/jason_zhouu_",
          "value": "jason_zhouu_",
          "timestamp": 1630189170
        }
      ]
    },
    {
      "title": "",
      "media_list_data": [
        
      ],
      "string_list_data": [
        {
          "href": "https://www.instagram.com/ria_upreti",
          "value": "ria_upreti",
          "timestamp": 1630189169
        }
      ]
    },
    {
      "title": "",
      "media_list_data": [
        
      ],
      "string_list_data": [
        {
          "href": "https://www.instagram.com/sheenp03",
          "value": "sheenp03",
          "timestamp": 1630189167
        }
      ]
    },
    {
      "title": "",
      "media_list_data": [
        
      ],
      "string_list_data": [
        {
          "href": "https://www.instagram.com/orrin.nirro",
          "value": "orrin.nirro",
          "timestamp": 1630028455
        }
      ]
    },
    {
      "title": "",
      "media_list_data": [
        
      ],
      "string_list_data": [
        {
          "href": "https://www.instagram.com/kelvincaoyx",
          "value": "kelvincaoyx",
          "timestamp": 1630028446
        }
      ]
    },
    {
      "title": "",
      "media_list_data": [
        
      ],
      "string_list_data": [
        {
          "href": "https://www.instagram.com/128shirley.li",
          "value": "128shirley.li",
          "timestamp": 1630028435
        }
      ]
    },
    {
      "title": "",
      "media_list_data": [
        
      ],
      "string_list_data": [
        {
          "href": "https://www.instagram.com/tau_frosh_2t1",
          "value": "tau_frosh_2t1",
          "timestamp": 1629735347
        }
      ]
    },
    {
      "title": "",
      "media_list_data": [
        
      ],
      "string_list_data": [
        {
          "href": "https://www.instagram.com/_zx_zu_",
          "value": "_zx_zu_",
          "timestamp": 1629139632
        }
      ]
    },
    {
      "title": "",
      "media_list_data": [
        
      ],
      "string_list_data": [
        {
          "href": "https://www.instagram.com/squilliam_tess",
          "value": "squilliam_tess",
          "timestamp": 1627402634
        }
      ]
    },
    {
      "title": "",
      "media_list_data": [
        
      ],
      "string_list_data": [
        {
          "href": "https://www.instagram.com/j.fam527",
          "value": "j.fam527",
          "timestamp": 1626883101
        }
      ]
    },
    {
      "title": "",
      "media_list_data": [
        
      ],
      "string_list_data": [
        {
          "href": "https://www.instagram.com/resetmobility",
          "value": "resetmobility",
          "timestamp": 1626443732
        }
      ]
    },
    {
      "title": "",
      "media_list_data": [
        
      ],
      "string_list_data": [
        {
          "href": "https://www.instagram.com/_cjancheta",
          "value": "_cjancheta",
          "timestamp": 1626443717
        }
      ]
    },
    {
      "title": "",
      "media_list_data": [
        
      ],
      "string_list_data": [
        {
          "href": "https://www.instagram.com/liam_coolkid03",
          "value": "liam_coolkid03",
          "timestamp": 1625680962
        }
      ]
    },
    {
      "title": "",
      "media_list_data": [
        
      ],
      "string_list_data": [
        {
          "href": "https://www.instagram.com/michael.ngx",
          "value": "michael.ngx",
          "timestamp": 1625680802
        }
      ]
    },
    {
      "title": "",
      "media_list_data": [
        
      ],
      "string_list_data": [
        {
          "href": "https://www.instagram.com/ll3w3ll",
          "value": "ll3w3ll",
          "timestamp": 1625017041
        }
      ]
    },
    {
      "title": "",
      "media_list_data": [
        
      ],
      "string_list_data": [
        {
          "href": "https://www.instagram.com/albertcookie302",
          "value": "albertcookie302",
          "timestamp": 1624731663
        }
      ]
    },
    {
      "title": "",
      "media_list_data": [
        
      ],
      "string_list_data": [
        {
          "href": "https://www.instagram.com/shmuly_40",
          "value": "shmuly_40",
          "timestamp": 1624649521
        }
      ]
    },
    {
      "title": "",
      "media_list_data": [
        
      ],
      "string_list_data": [
        {
          "href": "https://www.instagram.com/brynfu",
          "value": "brynfu",
          "timestamp": 1624045712
        }
      ]
    },
    {
      "title": "",
      "media_list_data": [
        
      ],
      "string_list_data": [
        {
          "href": "https://www.instagram.com/captainfifi_",
          "value": "captainfifi_",
          "timestamp": 1623820680
        }
      ]
    },
    {
      "title": "",
      "media_list_data": [
        
      ],
      "string_list_data": [
        {
          "href": "https://www.instagram.com/ma.ahn",
          "value": "ma.ahn",
          "timestamp": 1623631547
        }
      ]
    },
    {
      "title": "",
      "media_list_data": [
        
      ],
      "string_list_data": [
        {
          "href": "https://www.instagram.com/froshweek",
          "value": "froshweek",
          "timestamp": 1623544532
        }
      ]
    },
    {
      "title": "",
      "media_list_data": [
        
      ],
      "string_list_data": [
        {
          "href": "https://www.instagram.com/eenheo",
          "value": "eenheo",
          "timestamp": 1623544531
        }
      ]
    },
    {
      "title": "",
      "media_list_data": [
        
      ],
      "string_list_data": [
        {
          "href": "https://www.instagram.com/meme.lliu",
          "value": "meme.lliu",
          "timestamp": 1623435925
        }
      ]
    },
    {
      "title": "",
      "media_list_data": [
        
      ],
      "string_list_data": [
        {
          "href": "https://www.instagram.com/em_i.l.y",
          "value": "em_i.l.y",
          "timestamp": 1623427277
        }
      ]
    },
    {
      "title": "",
      "media_list_data": [
        
      ],
      "string_list_data": [
        {
          "href": "https://www.instagram.com/jas.ngo",
          "value": "jas.ngo",
          "timestamp": 1622924210
        }
      ]
    },
    {
      "title": "",
      "media_list_data": [
        
      ],
      "string_list_data": [
        {
          "href": "https://www.instagram.com/marcofieromonte",
          "value": "marcofieromonte",
          "timestamp": 1622908773
        }
      ]
    },
    {
      "title": "",
      "media_list_data": [
        
      ],
      "string_list_data": [
        {
          "href": "https://www.instagram.com/ouronada",
          "value": "ouronada",
          "timestamp": 1616681483
        }
      ]
    },
    {
      "title": "",
      "media_list_data": [
        
      ],
      "string_list_data": [
        {
          "href": "https://www.instagram.com/ivan_tse967",
          "value": "ivan_tse967",
          "timestamp": 1616636742
        }
      ]
    },
    {
      "title": "",
      "media_list_data": [
        
      ],
      "string_list_data": [
        {
          "href": "https://www.instagram.com/uoftfriends25",
          "value": "uoftfriends25",
          "timestamp": 1616586337
        }
      ]
    },
    {
      "title": "",
      "media_list_data": [
        
      ],
      "string_list_data": [
        {
          "href": "https://www.instagram.com/colinlinhares",
          "value": "colinlinhares",
          "timestamp": 1605451350
        }
      ]
    },
    {
      "title": "",
      "media_list_data": [
        
      ],
      "string_list_data": [
        {
          "href": "https://www.instagram.com/chaminade_alumni",
          "value": "chaminade_alumni",
          "timestamp": 1604186651
        }
      ]
    },
    {
      "title": "",
      "media_list_data": [
        
      ],
      "string_list_data": [
        {
          "href": "https://www.instagram.com/pngo_",
          "value": "pngo_",
          "timestamp": 1601247415
        }
      ]
    },
    {
      "title": "",
      "media_list_data": [
        
      ],
      "string_list_data": [
        {
          "href": "https://www.instagram.com/busta0gel",
          "value": "busta0gel",
          "timestamp": 1601064166
        }
      ]
    },
    {
      "title": "",
      "media_list_data": [
        
      ],
      "string_list_data": [
        {
          "href": "https://www.instagram.com/ng7054",
          "value": "ng7054",
          "timestamp": 1600217380
        }
      ]
    },
    {
      "title": "",
      "media_list_data": [
        
      ],
      "string_list_data": [
        {
          "href": "https://www.instagram.com/ar.tr_",
          "value": "ar.tr_",
          "timestamp": 1600126240
        }
      ]
    },
    {
      "title": "",
      "media_list_data": [
        
      ],
      "string_list_data": [
        {
          "href": "https://www.instagram.com/dan_tran7",
          "value": "dan_tran7",
          "timestamp": 1600095179
        }
      ]
    },
    {
      "title": "",
      "media_list_data": [
        
      ],
      "string_list_data": [
        {
          "href": "https://www.instagram.com/christianm_racco",
          "value": "christianm_racco",
          "timestamp": 1600064830
        }
      ]
    },
    {
      "title": "",
      "media_list_data": [
        
      ],
      "string_list_data": [
        {
          "href": "https://www.instagram.com/methewhyun",
          "value": "methewhyun",
          "timestamp": 1600064830
        }
      ]
    },
    {
      "title": "",
      "media_list_data": [
        
      ],
      "string_list_data": [
        {
          "href": "https://www.instagram.com/noelfawns",
          "value": "noelfawns",
          "timestamp": 1599736439
        }
      ]
    },
    {
      "title": "",
      "media_list_data": [
        
      ],
      "string_list_data": [
        {
          "href": "https://www.instagram.com/kyleeriksen",
          "value": "kyleeriksen",
          "timestamp": 1599650033
        }
      ]
    },
    {
      "title": "",
      "media_list_data": [
        
      ],
      "string_list_data": [
        {
          "href": "https://www.instagram.com/communicativepurposes",
          "value": "communicativepurposes",
          "timestamp": 1598930303
        }
      ]
    },
    {
      "title": "",
      "media_list_data": [
        
      ],
      "string_list_data": [
        {
          "href": "https://www.instagram.com/thechaos_king",
          "value": "thechaos_king",
          "timestamp": 1598402989
        }
      ]
    },
    {
      "title": "",
      "media_list_data": [
        
      ],
      "string_list_data": [
        {
          "href": "https://www.instagram.com/_jacobgomes_",
          "value": "_jacobgomes_",
          "timestamp": 1598402983
        }
      ]
    },
    {
      "title": "",
      "media_list_data": [
        
      ],
      "string_list_data": [
        {
          "href": "https://www.instagram.com/putakelsmo",
          "value": "putakelsmo",
          "timestamp": 1597931076
        }
      ]
    },
    {
      "title": "",
      "media_list_data": [
        
      ],
      "string_list_data": [
        {
          "href": "https://www.instagram.com/swaggyykim",
          "value": "swaggyykim",
          "timestamp": 1597859856
        }
      ]
    },
    {
      "title": "",
      "media_list_data": [
        
      ],
      "string_list_data": [
        {
          "href": "https://www.instagram.com/kimnguven",
          "value": "kimnguven",
          "timestamp": 1597804119
        }
      ]
    },
    {
      "title": "",
      "media_list_data": [
        
      ],
      "string_list_data": [
        {
          "href": "https://www.instagram.com/lucase_111",
          "value": "lucase_111",
          "timestamp": 1593783771
        }
      ]
    },
    {
      "title": "",
      "media_list_data": [
        
      ],
      "string_list_data": [
        {
          "href": "https://www.instagram.com/cordelia.ngo_",
          "value": "cordelia.ngo_",
          "timestamp": 1588609473
        }
      ]
    },
    {
      "title": "",
      "media_list_data": [
        
      ],
      "string_list_data": [
        {
          "href": "https://www.instagram.com/jhus.28",
          "value": "jhus.28",
          "timestamp": 1585349027
        }
      ]
    },
    {
      "title": "",
      "media_list_data": [
        
      ],
      "string_list_data": [
        {
          "href": "https://www.instagram.com/stinkybabycsgotournament2021",
          "value": "stinkybabycsgotournament2021",
          "timestamp": 1584768620
        }
      ]
    },
    {
      "title": "",
      "media_list_data": [
        
      ],
      "string_list_data": [
        {
          "href": "https://www.instagram.com/_quangggggvooooooo_",
          "value": "_quangggggvooooooo_",
          "timestamp": 1583037840
        }
      ]
    },
    {
      "title": "",
      "media_list_data": [
        
      ],
      "string_list_data": [
        {
          "href": "https://www.instagram.com/alezandra_342",
          "value": "alezandra_342",
          "timestamp": 1581964904
        }
      ]
    },
    {
      "title": "",
      "media_list_data": [
        
      ],
      "string_list_data": [
        {
          "href": "https://www.instagram.com/bleronbojku01",
          "value": "bleronbojku01",
          "timestamp": 1581728042
        }
      ]
    },
    {
      "title": "",
      "media_list_data": [
        
      ],
      "string_list_data": [
        {
          "href": "https://www.instagram.com/aendru_nwuen",
          "value": "aendru_nwuen",
          "timestamp": 1579143205
        }
      ]
    },
    {
      "title": "",
      "media_list_data": [
        
      ],
      "string_list_data": [
        {
          "href": "https://www.instagram.com/_patrat_",
          "value": "_patrat_",
          "timestamp": 1577770649
        }
      ]
    },
    {
      "title": "",
      "media_list_data": [
        
      ],
      "string_list_data": [
        {
          "href": "https://www.instagram.com/murxll._",
          "value": "murxll._",
          "timestamp": 1577643619
        }
      ]
    },
    {
      "title": "",
      "media_list_data": [
        
      ],
      "string_list_data": [
        {
          "href": "https://www.instagram.com/faye.faye",
          "value": "faye.faye",
          "timestamp": 1577558460
        }
      ]
    },
    {
      "title": "",
      "media_list_data": [
        
      ],
      "string_list_data": [
        {
          "href": "https://www.instagram.com/daniel0santos009",
          "value": "daniel0santos009",
          "timestamp": 1576477214
        }
      ]
    },
    {
      "title": "",
      "media_list_data": [
        
      ],
      "string_list_data": [
        {
          "href": "https://www.instagram.com/aidenjtrinidad",
          "value": "aidenjtrinidad",
          "timestamp": 1575754284
        }
      ]
    },
    {
      "title": "",
      "media_list_data": [
        
      ],
      "string_list_data": [
        {
          "href": "https://www.instagram.com/tyjetherealist",
          "value": "tyjetherealist",
          "timestamp": 1575334017
        }
      ]
    },
    {
      "title": "",
      "media_list_data": [
        
      ],
      "string_list_data": [
        {
          "href": "https://www.instagram.com/mr_cioffi",
          "value": "mr_cioffi",
          "timestamp": 1574815299
        }
      ]
    },
    {
      "title": "",
      "media_list_data": [
        
      ],
      "string_list_data": [
        {
          "href": "https://www.instagram.com/_anthonyalfino",
          "value": "_anthonyalfino",
          "timestamp": 1574740579
        }
      ]
    },
    {
      "title": "",
      "media_list_data": [
        
      ],
      "string_list_data": [
        {
          "href": "https://www.instagram.com/michael.bocale17",
          "value": "michael.bocale17",
          "timestamp": 1574220715
        }
      ]
    },
    {
      "title": "",
      "media_list_data": [
        
      ],
      "string_list_data": [
        {
          "href": "https://www.instagram.com/someguynamedjonas",
          "value": "someguynamedjonas",
          "timestamp": 1573694302
        }
      ]
    },
    {
      "title": "",
      "media_list_data": [
        
      ],
      "string_list_data": [
        {
          "href": "https://www.instagram.com/tiagodinis7",
          "value": "tiagodinis7",
          "timestamp": 1573526093
        }
      ]
    },
    {
      "title": "",
      "media_list_data": [
        
      ],
      "string_list_data": [
        {
          "href": "https://www.instagram.com/jienterence.l",
          "value": "jienterence.l",
          "timestamp": 1573423254
        }
      ]
    },
    {
      "title": "",
      "media_list_data": [
        
      ],
      "string_list_data": [
        {
          "href": "https://www.instagram.com/sam_chapeau",
          "value": "sam_chapeau",
          "timestamp": 1573415337
        }
      ]
    },
    {
      "title": "",
      "media_list_data": [
        
      ],
      "string_list_data": [
        {
          "href": "https://www.instagram.com/hnirt_nathanoj",
          "value": "hnirt_nathanoj",
          "timestamp": 1573167831
        }
      ]
    },
    {
      "title": "",
      "media_list_data": [
        
      ],
      "string_list_data": [
        {
          "href": "https://www.instagram.com/patrick_pantalone",
          "value": "patrick_pantalone",
          "timestamp": 1573086971
        }
      ]
    },
    {
      "title": "",
      "media_list_data": [
        
      ],
      "string_list_data": [
        {
          "href": "https://www.instagram.com/kneecolespam",
          "value": "kneecolespam",
          "timestamp": 1572746772
        }
      ]
    },
    {
      "title": "",
      "media_list_data": [
        
      ],
      "string_list_data": [
        {
          "href": "https://www.instagram.com/michiyogm",
          "value": "michiyogm",
          "timestamp": 1572210291
        }
      ]
    },
    {
      "title": "",
      "media_list_data": [
        
      ],
      "string_list_data": [
        {
          "href": "https://www.instagram.com/johann_train_27",
          "value": "johann_train_27",
          "timestamp": 1572006426
        }
      ]
    },
    {
      "title": "",
      "media_list_data": [
        
      ],
      "string_list_data": [
        {
          "href": "https://www.instagram.com/edzeil.mendoza",
          "value": "edzeil.mendoza",
          "timestamp": 1571834661
        }
      ]
    },
    {
      "title": "",
      "media_list_data": [
        
      ],
      "string_list_data": [
        {
          "href": "https://www.instagram.com/patrickcareyy",
          "value": "patrickcareyy",
          "timestamp": 1571802089
        }
      ]
    },
    {
      "title": "",
      "media_list_data": [
        
      ],
      "string_list_data": [
        {
          "href": "https://www.instagram.com/___shanec",
          "value": "___shanec",
          "timestamp": 1571418490
        }
      ]
    },
    {
      "title": "",
      "media_list_data": [
        
      ],
      "string_list_data": [
        {
          "href": "https://www.instagram.com/zucchet_",
          "value": "zucchet_",
          "timestamp": 1571105640
        }
      ]
    },
    {
      "title": "",
      "media_list_data": [
        
      ],
      "string_list_data": [
        {
          "href": "https://www.instagram.com/_jes.ter_",
          "value": "_jes.ter_",
          "timestamp": 1571062817
        }
      ]
    },
    {
      "title": "",
      "media_list_data": [
        
      ],
      "string_list_data": [
        {
          "href": "https://www.instagram.com/_quang.vx_",
          "value": "_quang.vx_",
          "timestamp": 1570762963
        }
      ]
    },
    {
      "title": "",
      "media_list_data": [
        
      ],
      "string_list_data": [
        {
          "href": "https://www.instagram.com/dylanxchu",
          "value": "dylanxchu",
          "timestamp": 1570659830
        }
      ]
    },
    {
      "title": "",
      "media_list_data": [
        
      ],
      "string_list_data": [
        {
          "href": "https://www.instagram.com/marcos.de.leon",
          "value": "marcos.de.leon",
          "timestamp": 1570634275
        }
      ]
    },
    {
      "title": "",
      "media_list_data": [
        
      ],
      "string_list_data": [
        {
          "href": "https://www.instagram.com/nicoleebolante",
          "value": "nicoleebolante",
          "timestamp": 1570388330
        }
      ]
    },
    {
      "title": "",
      "media_list_data": [
        
      ],
      "string_list_data": [
        {
          "href": "https://www.instagram.com/s_thierry_",
          "value": "s_thierry_",
          "timestamp": 1558195637
        }
      ]
    },
    {
      "title": "",
      "media_list_data": [
        
      ],
      "string_list_data": [
        {
          "href": "https://www.instagram.com/ray_raldo",
          "value": "ray_raldo",
          "timestamp": 1554493398
        }
      ]
    },
    {
      "title": "",
      "media_list_data": [
        
      ],
      "string_list_data": [
        {
          "href": "https://www.instagram.com/ilz_kayla",
          "value": "ilz_kayla",
          "timestamp": 1539152021
        }
      ]
    },
    {
      "title": "",
      "media_list_data": [
        
      ],
      "string_list_data": [
        {
          "href": "https://www.instagram.com/janeell.b",
          "value": "janeell.b",
          "timestamp": 1538954691
        }
      ]
    },
    {
      "title": "",
      "media_list_data": [
        
      ],
      "string_list_data": [
        {
          "href": "https://www.instagram.com/jngoaway",
          "value": "jngoaway",
          "timestamp": 1534257682
        }
      ]
    },
    {
      "title": "",
      "media_list_data": [
        
      ],
      "string_list_data": [
        {
          "href": "https://www.instagram.com/jasmineengoo",
          "value": "jasmineengoo",
          "timestamp": 1534125018
        }
      ]
    },
    {
      "title": "",
      "media_list_data": [
        
      ],
      "string_list_data": [
        {
          "href": "https://www.instagram.com/isaaac.o",
          "value": "isaaac.o",
          "timestamp": 1534023051
        }
      ]
    },
    {
      "title": "",
      "media_list_data": [
        
      ],
      "string_list_data": [
        {
          "href": "https://www.instagram.com/quan.r_",
          "value": "quan.r_",
          "timestamp": 1533956585
        }
      ]
    },
    {
      "title": "",
      "media_list_data": [
        
      ],
      "string_list_data": [
        {
          "href": "https://www.instagram.com/donghabs98",
          "value": "donghabs98",
          "timestamp": 1533955764
        }
      ]
    }
  ]
}